group_label_local/GroupLabel.py
group_label_local/LabelConstants.py
group_label_local/__init__.py
group_label_local-0.0.12.dist-info/METADATA
group_label_local-0.0.12.dist-info/WHEEL
group_label_local-0.0.12.dist-info/top_level.txt
group_label_local-0.0.12.dist-info/RECORD
