Metadata-Version: 2.1
Name: group-label-local
Version: 0.0.12
Summary: PyPI Package for Circles group-label-local Python
Home-page: https://github.com/circles-zone/group-label-local-python-package
Author: Circles
Author-email: info@circlez.ai
Classifier: Programming Language :: Python :: 3
Classifier: License :: Other/Proprietary License
Classifier: Operating System :: OS Independent
Requires-Dist: logger-local >=0.0.135
Requires-Dist: database-mysql-local >=0.0.290
